ranlib/__init__.py
ranlib/constants.py
ranlib/utils.py
ranlib/_external/README.md
ranlib/_external/__init__.py
ranlib/_external/inits.py
ranlib/_external/install_checks.py
ranlib/_generated/__init__.py
ranlib/_generated/lib_dependencies.py
ranlib/actions/__init__.py
ranlib/actions/authentication.py
ranlib/actions/initialization.py
ranlib/actions/integrations.py
ranlib/actions/modify_papers.py
ranlib/actions/publish/__init__.py
ranlib/actions/publish/gather_entry.py
ranlib/actions/publish/push_entry.py
ranlib/cli/__init__.py
ranlib/cli/helpers.py
ranlib/cli/main.py
ranlib/cli/subcmds/__init__.py
ranlib/cli/subcmds/auth.py
ranlib/cli/subcmds/dev.py
ranlib/compilation/__init__.py
ranlib/compilation/abs2relimports.py
ranlib/compilation/compiler.py
ranlib/compilation/schemas.py
ranlib/core/__init__.py
ranlib/core/ranruntime.py
ranlib/state/__init__.py
ranlib/state/dotran.py
ranlib/state/pathutils.py
ranlib/state/ranstate.py
ranlib/state/dependencies/__init__.py
ranlib/state/dependencies/package_installation.py
ranlib/state/dependencies/paper_info_retrieval.py
ranlib/state/dependencies/preresolution.py
ranlib-0.0.15.dist-info/METADATA
ranlib-0.0.15.dist-info/WHEEL
ranlib-0.0.15.dist-info/entry_points.txt
ranlib-0.0.15.dist-info/licenses/LICENSE
ranlib-0.0.15.dist-info/RECORD
