Metadata-Version: 2.3
Name: ranlib
Version: 0.0.15
Summary: RAN library
Project-URL: Repository, https://github.com/ran-labs/ranlib
Project-URL: Changelog, https://github.com/ran-labs/ranlib/blob/main/CHANGELOG.md
Project-URL: Homepage, https://ran.so
Project-URL: Documentation, https://ran.so/docs
Project-URL: Source, https://github.com/ran-labs/ranlib
Project-URL: Tracker, https://github.com/ran-labs/ranlib/issues
Project-URL: Twitter, https://twitter.com/RANdotSO
Author-email: AmeerArsala <ameer.arsala03@gmail.com>, ShanMehr <ishanmeher25@gmail.com>
License:                                  Apache License
License-File: LICENSE
Requires-Python: >=3.9
Requires-Dist: gitpython<3.2,>=3.1.43
Requires-Dist: httpx<0.28,>=0.27.2
Requires-Dist: pydantic<2.9,>=2.8.2
Requires-Dist: rich<13.8,>=13.7.1
Requires-Dist: tomli-w<1.1,>=1.0.0
Requires-Dist: tomli<2.1,>=2.0.1
Requires-Dist: typer<0.13,>=0.12.3
Provides-Extra: fdev
Requires-Dist: hatch<2,>=1.12.0; extra == 'fdev'
Requires-Dist: jupytext<2,>=1.16.4; extra == 'fdev'
Requires-Dist: pybashify<0.2,>=0.1.1; extra == 'fdev'
Requires-Dist: pytest<9,>=8.3.2; extra == 'fdev'
Requires-Dist: ruff<0.7,>=0.6.8; extra == 'fdev'
